unidown/__init__.py
unidown/main.py
unidown/meta.py
unidown/tools.py
unidown/core/__init__.py
unidown/core/manager.py
unidown/core/plugin_state.py
unidown/core/settings.py
unidown/core/updater.py
unidown/plugin/__init__.py
unidown/plugin/a_plugin.py
unidown/plugin/exceptions.py
unidown/plugin/link_item.py
unidown/plugin/link_item_dict.py
unidown/plugin/plugin_info.py
unidown/plugin/savestate.py
unidown-2.1.0.dist-info/LICENSE.md
unidown-2.1.0.dist-info/METADATA
unidown-2.1.0.dist-info/WHEEL
unidown-2.1.0.dist-info/entry_points.txt
unidown-2.1.0.dist-info/top_level.txt
unidown-2.1.0.dist-info/zip-safe
unidown-2.1.0.dist-info/RECORD
