Metadata-Version: 2.1
Name: unidown
Version: 2.1.0
Summary: Universal downloader, a modular extensible downloader who manage progress and updates.
Home-page: https://github.com/IceflowRE/unidown
Author: Iceflower S
Author-email: iceflower@gmx.de
License: GPLv3
Keywords: modular downloader
Classifier: Programming Language :: Python :: 3.11
Classifier: License :: OSI Approved :: GNU General Public License v3 (GPLv3)
Classifier: Development Status :: 5 - Production/Stable
Classifier: Operating System :: OS Independent
Classifier: Intended Audience :: Developers
Classifier: Intended Audience :: End Users/Desktop
Classifier: Natural Language :: English
Classifier: Environment :: Console
Requires-Python: >=3.11
License-File: LICENSE.md
Requires-Dist: urllib3 >=1.26.12
Requires-Dist: tqdm >=4.64.1
Requires-Dist: packaging >=21.3
Provides-Extra: dev
Requires-Dist: flake8 ; extra == 'dev'
Requires-Dist: wemake-python-styleguide ; extra == 'dev'
Requires-Dist: flake8-2020 ; extra == 'dev'
Requires-Dist: flake8-builtins ; extra == 'dev'
Requires-Dist: flake8-comprehensions ; extra == 'dev'
Requires-Dist: flake8-docstrings ; extra == 'dev'
Requires-Dist: flake8-multiline-containers ; extra == 'dev'
Requires-Dist: flake8-use-fstring ; extra == 'dev'
Requires-Dist: flake8-simplify ; extra == 'dev'
Requires-Dist: mypy ; extra == 'dev'
Requires-Dist: types-certifi ; extra == 'dev'
Requires-Dist: types-urllib3 ; extra == 'dev'
Requires-Dist: types-setuptools ; extra == 'dev'
Requires-Dist: pylint ; extra == 'dev'
Requires-Dist: pyroma ; extra == 'dev'
Requires-Dist: pytest >=7.1.3 ; extra == 'dev'
Requires-Dist: pytest-cov >=3.0.0 ; extra == 'dev'
Requires-Dist: setuptools ; extra == 'dev'
Requires-Dist: twine >=4.0.1 ; extra == 'dev'
Provides-Extra: doc
Requires-Dist: Sphinx >=5.1.1 ; extra == 'doc'
Requires-Dist: sphinx-autodoc-typehints >=1.19.2 ; extra == 'doc'
Requires-Dist: sphinx-rtd-theme >=1.0.0 ; extra == 'doc'
Requires-Dist: sphinxcontrib-mermaid >=0.7.1 ; extra == 'doc'
